planit_py/__init__.py
planit_py/_version.py
planit_py/ors.py
planit_py-0.0.1.dist-info/METADATA
planit_py-0.0.1.dist-info/WHEEL
planit_py-0.0.1.dist-info/licenses/LICENSE
planit_py-0.0.1.dist-info/RECORD
