Metadata-Version: 2.4
Name: planit-py
Version: 0.0.1
Summary: A Python library to plan exoplanet observations.
Project-URL: Homepage, https://github.com/CoreySpohn/planit-py
Project-URL: Issues, https://github.com/CoreySpohn/planit-py/issues
Author-email: Corey Spohn <corey.a.spohn@nasa.gov>
License: MIT License
License-File: LICENSE
Classifier: Intended Audience :: Science/Research
Classifier: License :: OSI Approved :: MIT License
Classifier: Programming Language :: Python :: 3
Classifier: Topic :: Scientific/Engineering :: Astronomy
Requires-Python: >=3.9
Requires-Dist: astropy
Requires-Dist: or-tools
Provides-Extra: docs
Requires-Dist: matplotlib; extra == 'docs'
Requires-Dist: myst-nb; extra == 'docs'
Requires-Dist: sphinx; extra == 'docs'
Requires-Dist: sphinx-autoapi; extra == 'docs'
Requires-Dist: sphinx-autodoc-typehints; extra == 'docs'
Requires-Dist: sphinx-book-theme; extra == 'docs'
Provides-Extra: test
Requires-Dist: hypothesis; extra == 'test'
Requires-Dist: nox; extra == 'test'
Requires-Dist: pytest; extra == 'test'
Requires-Dist: pytest-cov; extra == 'test'
